invokees/__init__.py
invokees/files.py
invokees/tasks/__init__.py
invokees/tasks/code.py
invokees/tasks/docs.py
invokees/tasks/release.py
invokees/tasks/self.py
invokees/tasks/test.py
invokees/tools/__init__.py
invokees-0.4.0.dist-info/WHEEL
invokees-0.4.0.dist-info/METADATA
invokees-0.4.0.dist-info/RECORD
